dos/__init__.py
dos/flask_wrappers.py
dos/open_api.py
dos/parsers.py
dos/prop.py
dos/prop_wrapper.py
dos/schema.py
dos/validation_helpers.py
dos/validators.py
dos-1.6.0.dist-info/LICENSE
dos-1.6.0.dist-info/METADATA
dos-1.6.0.dist-info/WHEEL
dos-1.6.0.dist-info/top_level.txt
dos-1.6.0.dist-info/RECORD
