Metadata-Version: 2.1
Name: dos
Version: 1.6.0
Summary: Document and Validate Flask
Home-page: https://github.com/pr/dos
Author: Peter Richards
Author-email: dos@peter.net
License: MIT
Platform: UNKNOWN
Classifier: Programming Language :: Python :: 3
Classifier: License :: OSI Approved :: MIT License
Classifier: Operating System :: OS Independent
Requires-Python: >=3.1
Requires-Dist: arrow
Requires-Dist: flask
